dynamic_typer/__init__.py
dynamic_typer/__version__.py
dynamic_typer/dynamic_typer.py
dynamic_typer/py.typed
dynamic_typer-0.1.1.dist-info/METADATA
dynamic_typer-0.1.1.dist-info/WHEEL
dynamic_typer-0.1.1.dist-info/licenses/LICENSE
dynamic_typer-0.1.1.dist-info/RECORD
